py_img_gen/__init__.py
py_img_gen/typehints.py
py_img_gen/datasets/__init__.py
py_img_gen/datasets/dreambooth.py
py_img_gen/datasets/fashion_mnist.py
py_img_gen/datasets/skimage.py
py_img_gen/datasets/textual_inversion.py
py_img_gen/inferencers/__init__.py
py_img_gen/inferencers/diffusion.py
py_img_gen/inferencers/inference_module.py
py_img_gen/trainers/__init__.py
py_img_gen/trainers/config.py
py_img_gen/trainers/diffusion.py
py_img_gen/trainers/loss_modules.py
py_img_gen/trainers/transformers.py
py_img_gen/training/__init__.py
py_img_gen/training/accelerator.py
py_img_gen/training/dreambooth.py
py_img_gen/training/hyperparameter.py
py_img_gen/training/lora.py
py_img_gen/training/textual_inversion.py
py_img_gen/training/utils.py
py_img_gen/utils/__init__.py
py_img_gen/utils/download.py
py_img_gen/utils/image.py
py_img_gen/utils/testing.py
py_img_gen/utils/tokenization.py
py_img_gen/utils/visualization.py
py_img_gen/utils/warnings.py
py_img_gen-0.1.0.dist-info/METADATA
py_img_gen-0.1.0.dist-info/WHEEL
py_img_gen-0.1.0.dist-info/RECORD
